Metadata-Version: 2.1
Name: pyconfigstore3
Version: 1.0.1
Summary: A Python module for handling config files. It helps handles persist config files and also giving the ability to set, get, update and delete config settings its based on Configstore.js
Home-page: https://github.com/CITGuru/ConfigStore
Author: Oyetoke Toby
Author-email: oyetoketoby80@gmail.com
License: MIT
Download-URL: https://github.com/CITGuru/ConfigStore/archive/1.0.0.tar.gz
Keywords: config,settings,.env,json,settings,configstore
Platform: UNKNOWN
Classifier: Development Status :: 1 - Planning
Classifier: Natural Language :: English
Classifier: Programming Language :: Python :: 2.7
Classifier: Programming Language :: Python :: 3.6
Classifier: Environment :: Console
Classifier: Intended Audience :: Developers
Classifier: License :: OSI Approved :: MIT License
Classifier: Operating System :: OS Independent
Classifier: Topic :: Software Development :: User Interfaces
Classifier: Topic :: Software Development :: Libraries :: Application Frameworks
